stemlab/__init__.py
stemlab/utils.py
stemlab/biology/__init__.py
stemlab/biology/core.py
stemlab/chemistry/__init__.py
stemlab/chemistry/core.py
stemlab/core/__init__.py
stemlab/core/arraylike.py
stemlab/core/css.py
stemlab/core/datatypes.py
stemlab/core/datetime.py
stemlab/core/decimals.py
stemlab/core/display.py
stemlab/core/files.py
stemlab/core/forms.py
stemlab/core/htmlatex.py
stemlab/core/htmlstyles.py
stemlab/core/inputs.py
stemlab/core/latexstyles.py
stemlab/core/options.py
stemlab/core/output.py
stemlab/core/plotting.py
stemlab/core/prepareinputs.py
stemlab/core/symbolic.py
stemlab/core/variables.py
stemlab/core/base/__init__.py
stemlab/core/base/arrays.py
stemlab/core/base/computations.py
stemlab/core/base/constants.py
stemlab/core/base/constraints.py
stemlab/core/base/dictionaries.py
stemlab/core/base/functions.py
stemlab/core/base/lists.py
stemlab/core/base/numbers.py
stemlab/core/base/strings.py
stemlab/core/base/symbolic.py
stemlab/core/base/units.py
stemlab/core/graphs/__init__.py
stemlab/core/validators/__init__.py
stemlab/core/validators/arithmetic.py
stemlab/core/validators/errors.py
stemlab/core/validators/validate.py
stemlab/datasets/__init__.py
stemlab/datasets/readdatasets.py
stemlab/datasets/csv/NE.csv
stemlab/datasets/csv/NE1.csv
stemlab/datasets/csv/NW.csv
stemlab/datasets/csv/South.csv
stemlab/datasets/csv/West.csv
stemlab/datasets/csv/West1.csv
stemlab/datasets/csv/__init__.py
stemlab/datasets/csv/boole.csv
stemlab/datasets/csv/bronze.csv
stemlab/datasets/csv/cancer.csv
stemlab/datasets/csv/cancer2.csv
stemlab/datasets/csv/cash_columns.csv
stemlab/datasets/csv/cash_transfer.csv
stemlab/datasets/csv/cash_transfer2.csv
stemlab/datasets/csv/clean_values.csv
stemlab/datasets/csv/col_names.csv
stemlab/datasets/csv/cotes_n8.csv
stemlab/datasets/csv/countries.csv
stemlab/datasets/csv/data_dup.csv
stemlab/datasets/csv/data_random.csv
stemlab/datasets/csv/datasets.csv
stemlab/datasets/csv/df_income4.csv
stemlab/datasets/csv/emp.csv
stemlab-0.2.0.dist-info/LICENSE.txt
stemlab-0.2.0.dist-info/METADATA
stemlab-0.2.0.dist-info/WHEEL
stemlab-0.2.0.dist-info/top_level.txt
stemlab-0.2.0.dist-info/RECORD
