Metadata-Version: 2.1
Name: stemlab
Version: 0.2.0
Summary: A Python Library for Mathematical and Statistical Computing in STEM
Home-page: https://github.com/stemxresearch/stemlab
Author: STEM Research
Author-email: library@stemxresearch.com
License: MIT
Classifier: Programming Language :: Python :: 3
Classifier: License :: OSI Approved :: MIT License
Classifier: Operating System :: OS Independent
Requires-Python: >=3.6
License-File: LICENSE.txt
Requires-Dist: scipy
Requires-Dist: scikit-learn
Requires-Dist: plotly
Requires-Dist: sympy
Requires-Dist: IPython
Requires-Dist: statsmodels
Requires-Dist: kaleido
